input_form_dialog.py
input_form_dialog-1.0.1.dist-info/METADATA
input_form_dialog-1.0.1.dist-info/RECORD
input_form_dialog-1.0.1.dist-info/WHEEL
input_form_dialog-1.0.1.dist-info/top_level.txt
