Metadata-Version: 2.1
Name: input-form-dialog
Version: 1.0.1
Summary: InputFormDialog provides a simple multi-type input dialog for Qt5
Home-page: https://github.com/serguei-k/input-form-dialog/tree/master/python
Author: Serguei Kalentchouk
License: MIT
Platform: UNKNOWN
Requires-Dist: Qt.py
